midil/__init__.py
midil/auth/__init__.py
midil/auth/cognito/__init__.py
midil/auth/cognito/_exceptions.py
midil/auth/cognito/client_credentials_flow.py
midil/auth/cognito/jwt_authorizer.py
midil/auth/config.py
midil/auth/exceptions.py
midil/auth/interfaces/__init__.py
midil/auth/interfaces/authenticator.py
midil/auth/interfaces/authorizer.py
midil/auth/interfaces/models.py
midil/cli/commands/_common.py
midil/cli/commands/init.py
midil/cli/commands/launch.py
midil/cli/commands/test.py
midil/cli/commands/version.py
midil/cli/core/launchers/base.py
midil/cli/core/launchers/uvicorn.py
midil/cli/core/scaffolds/__init__.py
midil/cli/core/scaffolds/base.py
midil/cli/core/scaffolds/factory.py
midil/cli/core/scaffolds/fastapi.py
midil/cli/core/scaffolds/lambda_function.py
midil/cli/core/templates/cookiecutter-midil-project/cookiecutter.json
midil/cli/core/templates/cookiecutter-midil-project/extensions.py
midil/cli/core/templates/cookiecutter-midil-project/hooks/post_gen_project.py
midil/cli/core/templates/cookiecutter-midil-project/{{cookiecutter.project_slug}}/.env.example
midil/cli/core/templates/cookiecutter-midil-project/{{cookiecutter.project_slug}}/.gitignore
midil/cli/core/templates/cookiecutter-midil-project/{{cookiecutter.project_slug}}/README.md
midil/cli/core/templates/cookiecutter-midil-project/{{cookiecutter.project_slug}}/main.py
midil/cli/core/templates/cookiecutter-midil-project/{{cookiecutter.project_slug}}/poetry.toml
midil/cli/core/templates/cookiecutter-midil-project/{{cookiecutter.project_slug}}/pyproject.toml
midil/cli/core/templates/cookiecutter-midil-project/{{cookiecutter.project_slug}}/{% if cookiecutter.include_docker == 'y' %}Dockerfile{% endif %}
midil/cli/core/testing/builder.py
midil/cli/core/testing/options.py
midil/cli/core/testing/runner.py
midil/cli/main.py
midil/cli/utils.py
midil/event/__init__.py
midil/event/_examples/event_bus.py
midil/event/_examples/event_context.py
midil/event/_examples/standalone_consumer.py
midil_kit-3.4.3.dist-info/LICENSE
midil_kit-3.4.3.dist-info/METADATA
midil_kit-3.4.3.dist-info/WHEEL
midil_kit-3.4.3.dist-info/entry_points.txt
midil_kit-3.4.3.dist-info/RECORD
