Metadata-Version: 2.3
Name: midil-kit
Version: 3.4.3
Summary: A Python SDK for backend systems development @midil.io
Keywords: midil,midil-kit,event,infrastructure,extensions
Author: Engr. Michael Kofi Armah
Author-email: michael.armah@midil.io
Requires-Python: >=3.12,<4.0
Classifier: Development Status :: 3 - Alpha
Classifier: Intended Audience :: Developers
Classifier: License :: OSI Approved :: Apache Software License
Classifier: Programming Language :: Python :: 3
Classifier: Programming Language :: Python :: 3.12
Classifier: Programming Language :: Python :: 3.13
Classifier: Topic :: Software Development :: Libraries :: Python Modules
Classifier: Topic :: Utilities
Requires-Dist: aioboto3 (>=15.0.0,<16.0.0)
Requires-Dist: aiobotocore (>=2.10.0,<3.0.0)
Requires-Dist: aioredis (>=2.0.1,<3.0.0)
Requires-Dist: aiostream (>=0.7.0,<0.8.0)
Requires-Dist: click (>=8.1.7,<9.0.0)
Requires-Dist: cookiecutter (>=2.6.0,<3.0.0)
Requires-Dist: fastapi (>=0.116.1,<0.117.0)
Requires-Dist: httpx (>=0.28.1,<0.29.0)
Requires-Dist: loguru (>=0.7.3,<0.8.0)
Requires-Dist: pydantic (>=2.0.0,<3.0.0)
Requires-Dist: pydantic-settings (>=2.10.1,<3.0.0)
Requires-Dist: pyfiglet (>=1.0.4,<2.0.0)
Requires-Dist: pyjwt (>=2.10.1,<3.0.0)
Requires-Dist: python-dateutil (>=2.8.0,<3.0.0)
Requires-Dist: redis (>=5.2.1,<6.0.0)
Requires-Dist: rich (>=14.1.0,<15.0.0)
Requires-Dist: starlette (>=0.47.2,<0.48.0)
Requires-Dist: tenacity (>=9.1.2,<10.0.0)
Requires-Dist: tomli (>=2.2.1,<3.0.0)
Requires-Dist: types-aioboto3 (>=15.0.0,<16.0.0)
Requires-Dist: uvicorn (>=0.29.0,<0.30.0)
Requires-Dist: websockets (>=15.0.1,<16.0.0)
